endo_reg_db/__init__.py
endo_reg_db/admin.py
endo_reg_db/apps.py
endo_reg_db/main.py
endo_reg_db/migrations/__init__.py
endo_reg_db/models.py
endo_reg_db/tests.py
endo_reg_db/views.py
endo_reg_db-0.1.6.dist-info/LICENSE
endo_reg_db-0.1.6.dist-info/METADATA
endo_reg_db-0.1.6.dist-info/WHEEL
endo_reg_db-0.1.6.dist-info/RECORD
