Metadata-Version: 2.1
Name: endo-reg-db
Version: 0.1.6
Summary: Django App providing db backbone for the EndoReg Project
License: MIT
Author: Thomas J. Lux
Requires-Python: >=3.11,<4.0
Classifier: License :: OSI Approved :: MIT License
Classifier: Programming Language :: Python :: 3
Classifier: Programming Language :: Python :: 3.11
Classifier: Programming Language :: Python :: 3.12
Requires-Dist: django (>=4.2,<5.0)
